PyLidar2/__init__.py
PyLidar2-1.6.dist-info/LICENSE
PyLidar2-1.6.dist-info/METADATA
PyLidar2-1.6.dist-info/WHEEL
PyLidar2-1.6.dist-info/top_level.txt
PyLidar2-1.6.dist-info/RECORD
