Metadata-Version: 2.1
Name: PyLidar2
Version: 1.6
Summary: Library for Lidar. Currently supports YdLidar(X4,G4) from http://www.ydlidar.com
Home-page: https://github.com/lakshmanmallidi/PyLidar2
Author: Lakshman mallidi
Author-email: lakshman.mallidi@gmail.com
License: UNKNOWN
Platform: UNKNOWN
Classifier: Programming Language :: Python :: 2
Classifier: License :: OSI Approved :: MIT License
Classifier: Operating System :: OS Independent
Requires-Python: <3
Requires-Dist: pyserial
Requires-Dist: enum
